README.md
setup.py
old_major.egg-info/PKG-INFO
old_major.egg-info/SOURCES.txt
old_major.egg-info/dependency_links.txt
old_major.egg-info/entry_points.txt
old_major.egg-info/requires.txt
old_major.egg-info/top_level.txt
src/__init__.py
src/old_major/__init__.py
src/old_major/cmd.py
src/old_major/connection.py
src/old_major/led_debugger.py
src/old_major/parser.py