Metadata-Version: 1.0
Name: old-major
Version: 0.0.18
Summary: RICC project central system
Home-page: https://github.com/ricc-project/old-major
Author: UNKNOWN
Author-email: UNKNOWN
License: UNKNOWN
Platform: UNKNOWN
